{
    "inkVersion": 21,
    "root": [
        [
            {
                "->t->": "out"
            },
            {
                "->t->": "out"
            },
            {
                "->t->": "out"
            },
            {
                "->t->": "out"
            },
            {
                "->t->": "out"
            },
            "end",
            [
                "done",
                {
                    "#f": 5,
                    "#n": "g-0"
                }
            ],
            null
        ],
        "done",
        {
            "out": [
                [
                    "ev",
                    "visit",
                    4,
                    "MIN",
                    "/ev",
                    "ev",
                    "du",
                    0,
                    "==",
                    "/ev",
                    {
                        "->": ".^.s0",
                        "c": true
                    },
                    "ev",
                    "du",
                    1,
                    "==",
                    "/ev",
                    {
                        "->": ".^.s1",
                        "c": true
                    },
                    "ev",
                    "du",
                    2,
                    "==",
                    "/ev",
                    {
                        "->": ".^.s2",
                        "c": true
                    },
                    "ev",
                    "du",
                    3,
                    "==",
                    "/ev",
                    {
                        "->": ".^.s3",
                        "c": true
                    },
                    "ev",
                    "du",
                    4,
                    "==",
                    "/ev",
                    {
                        "->": ".^.s4",
                        "c": true
                    },
                    "nop",
                    {
                        "s0": [
                            "pop",
                            "^\"Three!\"",
                            {
                                "->": ".^.^.35"
                            },
                            null
                        ],
                        "s1": [
                            "pop",
                            "^\"Two!\"",
                            {
                                "->": ".^.^.35"
                            },
                            null
                        ],
                        "s2": [
                            "pop",
                            "^\"One!\"",
                            {
                                "->": ".^.^.35"
                            },
                            null
                        ],
                        "s3": [
                            "pop",
                            "^There was the white noise racket of an explosion.",
                            {
                                "->": ".^.^.35"
                            },
                            null
                        ],
                        "s4": [
                            "pop",
                            "^But it was just static.",
                            {
                                "->": ".^.^.35"
                            },
                            null
                        ],
                        "#f": 5
                    }
                ],
                "\n",
                "ev",
                "void",
                "/ev",
                "->->",
                {
                    "#f": 1
                }
            ],
            "#f": 1
        }
    ],
    "listDefs": {}
}